rdapi/__init__.py
rdapi/error_codes.json
rdapi/rdapi.py
rd_api_py-0.4.0.dist-info/LICENSE
rd_api_py-0.4.0.dist-info/METADATA
rd_api_py-0.4.0.dist-info/WHEEL
rd_api_py-0.4.0.dist-info/top_level.txt
rd_api_py-0.4.0.dist-info/RECORD
