Metadata-Version: 2.1
Name: rd-api-py
Version: 0.4.0
Summary: Real Debrid API Library for Python
Author: $krilla
Project-URL: Homepage, https://github.com/s-krilla/rd_api_py
Project-URL: Bug Tracker, https://github.com/s-krilla/rd_api_py/issues
Classifier: Programming Language :: Python :: 3
Classifier: License :: OSI Approved :: MIT License
Classifier: Operating System :: OS Independent
Requires-Python: >=3.8
License-File: LICENSE
Requires-Dist: requests ~=2.31.0
Requires-Dist: python-dotenv ~=1.0.0
